{"tactics": [],
 "premises": [],
 "commandASTs":
 [{"node":
   {"kind": "Lean.Parser.Module.header",
    "info": "none",
    "args":
    [{"node":
      {"kind": "null",
       "info": "none",
       "args":
       [{"node":
         {"kind": "Lean.Parser.Module.moduleTk",
          "info": "none",
          "args":
          [{"atom":
            {"val": "module",
             "info":
             {"original":
              {"trailing": "\n\n",
               "pos": 160,
               "leading": "",
               "endPos": 166}}}}]}}]}},
     {"node":
      {"kind": "null",
       "info": "none",
       "args":
       [{"node":
         {"kind": "Lean.Parser.Module.prelude",
          "info": "none",
          "args":
          [{"atom":
            {"val": "prelude",
             "info":
             {"original":
              {"trailing": "\n",
               "pos": 168,
               "leading": "",
               "endPos": 175}}}}]}}]}},
     {"node":
      {"kind": "null",
       "info": "none",
       "args":
       [{"node":
         {"kind": "Lean.Parser.Module.import",
          "info": "none",
          "args":
          [{"node": {"kind": "null", "info": "none", "args": []}},
           {"atom":
            {"val": "import",
             "info":
             {"original":
              {"trailing": " ", "pos": 176, "leading": "", "endPos": 182}}}},
           {"node": {"kind": "null", "info": "none", "args": []}},
           {"ident":
            {"val": "Init.Data.Array.Basic",
             "rawVal": "Init.Data.Array.Basic",
             "preresolved": [],
             "info":
             {"original":
              {"trailing": "\n", "pos": 183, "leading": "", "endPos": 204}}}},
           {"node": {"kind": "null", "info": "none", "args": []}}]}},
        {"node":
         {"kind": "Lean.Parser.Module.import",
          "info": "none",
          "args":
          [{"node": {"kind": "null", "info": "none", "args": []}},
           {"atom":
            {"val": "import",
             "info":
             {"original":
              {"trailing": " ", "pos": 205, "leading": "", "endPos": 211}}}},
           {"node": {"kind": "null", "info": "none", "args": []}},
           {"ident":
            {"val": "Init.Data.Array.QSort",
             "rawVal": "Init.Data.Array.QSort",
             "preresolved": [],
             "info":
             {"original":
              {"trailing": "\n", "pos": 212, "leading": "", "endPos": 233}}}},
           {"node": {"kind": "null", "info": "none", "args": []}}]}},
        {"node":
         {"kind": "Lean.Parser.Module.import",
          "info": "none",
          "args":
          [{"node": {"kind": "null", "info": "none", "args": []}},
           {"atom":
            {"val": "import",
             "info":
             {"original":
              {"trailing": " ", "pos": 234, "leading": "", "endPos": 240}}}},
           {"node": {"kind": "null", "info": "none", "args": []}},
           {"ident":
            {"val": "Init.Data.Array.BinSearch",
             "rawVal": "Init.Data.Array.BinSearch",
             "preresolved": [],
             "info":
             {"original":
              {"trailing": "\n", "pos": 241, "leading": "", "endPos": 266}}}},
           {"node": {"kind": "null", "info": "none", "args": []}}]}},
        {"node":
         {"kind": "Lean.Parser.Module.import",
          "info": "none",
          "args":
          [{"node": {"kind": "null", "info": "none", "args": []}},
           {"atom":
            {"val": "import",
             "info":
             {"original":
              {"trailing": " ", "pos": 267, "leading": "", "endPos": 273}}}},
           {"node": {"kind": "null", "info": "none", "args": []}},
           {"ident":
            {"val": "Init.Data.Array.InsertionSort",
             "rawVal": "Init.Data.Array.InsertionSort",
             "preresolved": [],
             "info":
             {"original":
              {"trailing": "\n", "pos": 274, "leading": "", "endPos": 303}}}},
           {"node": {"kind": "null", "info": "none", "args": []}}]}},
        {"node":
         {"kind": "Lean.Parser.Module.import",
          "info": "none",
          "args":
          [{"node": {"kind": "null", "info": "none", "args": []}},
           {"atom":
            {"val": "import",
             "info":
             {"original":
              {"trailing": " ", "pos": 304, "leading": "", "endPos": 310}}}},
           {"node": {"kind": "null", "info": "none", "args": []}},
           {"ident":
            {"val": "Init.Data.Array.DecidableEq",
             "rawVal": "Init.Data.Array.DecidableEq",
             "preresolved": [],
             "info":
             {"original":
              {"trailing": "\n", "pos": 311, "leading": "", "endPos": 338}}}},
           {"node": {"kind": "null", "info": "none", "args": []}}]}},
        {"node":
         {"kind": "Lean.Parser.Module.import",
          "info": "none",
          "args":
          [{"node": {"kind": "null", "info": "none", "args": []}},
           {"atom":
            {"val": "import",
             "info":
             {"original":
              {"trailing": " ", "pos": 339, "leading": "", "endPos": 345}}}},
           {"node": {"kind": "null", "info": "none", "args": []}},
           {"ident":
            {"val": "Init.Data.Array.Mem",
             "rawVal": "Init.Data.Array.Mem",
             "preresolved": [],
             "info":
             {"original":
              {"trailing": "\n", "pos": 346, "leading": "", "endPos": 365}}}},
           {"node": {"kind": "null", "info": "none", "args": []}}]}},
        {"node":
         {"kind": "Lean.Parser.Module.import",
          "info": "none",
          "args":
          [{"node": {"kind": "null", "info": "none", "args": []}},
           {"atom":
            {"val": "import",
             "info":
             {"original":
              {"trailing": " ", "pos": 366, "leading": "", "endPos": 372}}}},
           {"node": {"kind": "null", "info": "none", "args": []}},
           {"ident":
            {"val": "Init.Data.Array.Attach",
             "rawVal": "Init.Data.Array.Attach",
             "preresolved": [],
             "info":
             {"original":
              {"trailing": "\n", "pos": 373, "leading": "", "endPos": 395}}}},
           {"node": {"kind": "null", "info": "none", "args": []}}]}},
        {"node":
         {"kind": "Lean.Parser.Module.import",
          "info": "none",
          "args":
          [{"node": {"kind": "null", "info": "none", "args": []}},
           {"atom":
            {"val": "import",
             "info":
             {"original":
              {"trailing": " ", "pos": 396, "leading": "", "endPos": 402}}}},
           {"node": {"kind": "null", "info": "none", "args": []}},
           {"ident":
            {"val": "Init.Data.Array.BasicAux",
             "rawVal": "Init.Data.Array.BasicAux",
             "preresolved": [],
             "info":
             {"original":
              {"trailing": "\n", "pos": 403, "leading": "", "endPos": 427}}}},
           {"node": {"kind": "null", "info": "none", "args": []}}]}},
        {"node":
         {"kind": "Lean.Parser.Module.import",
          "info": "none",
          "args":
          [{"node": {"kind": "null", "info": "none", "args": []}},
           {"atom":
            {"val": "import",
             "info":
             {"original":
              {"trailing": " ", "pos": 428, "leading": "", "endPos": 434}}}},
           {"node": {"kind": "null", "info": "none", "args": []}},
           {"ident":
            {"val": "Init.Data.Array.Lemmas",
             "rawVal": "Init.Data.Array.Lemmas",
             "preresolved": [],
             "info":
             {"original":
              {"trailing": "\n", "pos": 435, "leading": "", "endPos": 457}}}},
           {"node": {"kind": "null", "info": "none", "args": []}}]}},
        {"node":
         {"kind": "Lean.Parser.Module.import",
          "info": "none",
          "args":
          [{"node": {"kind": "null", "info": "none", "args": []}},
           {"atom":
            {"val": "import",
             "info":
             {"original":
              {"trailing": " ", "pos": 458, "leading": "", "endPos": 464}}}},
           {"node": {"kind": "null", "info": "none", "args": []}},
           {"ident":
            {"val": "Init.Data.Array.TakeDrop",
             "rawVal": "Init.Data.Array.TakeDrop",
             "preresolved": [],
             "info":
             {"original":
              {"trailing": "\n", "pos": 465, "leading": "", "endPos": 489}}}},
           {"node": {"kind": "null", "info": "none", "args": []}}]}},
        {"node":
         {"kind": "Lean.Parser.Module.import",
          "info": "none",
          "args":
          [{"node": {"kind": "null", "info": "none", "args": []}},
           {"atom":
            {"val": "import",
             "info":
             {"original":
              {"trailing": " ", "pos": 490, "leading": "", "endPos": 496}}}},
           {"node": {"kind": "null", "info": "none", "args": []}},
           {"ident":
            {"val": "Init.Data.Array.Bootstrap",
             "rawVal": "Init.Data.Array.Bootstrap",
             "preresolved": [],
             "info":
             {"original":
              {"trailing": "\n", "pos": 497, "leading": "", "endPos": 522}}}},
           {"node": {"kind": "null", "info": "none", "args": []}}]}},
        {"node":
         {"kind": "Lean.Parser.Module.import",
          "info": "none",
          "args":
          [{"node": {"kind": "null", "info": "none", "args": []}},
           {"atom":
            {"val": "import",
             "info":
             {"original":
              {"trailing": " ", "pos": 523, "leading": "", "endPos": 529}}}},
           {"node": {"kind": "null", "info": "none", "args": []}},
           {"ident":
            {"val": "Init.Data.Array.GetLit",
             "rawVal": "Init.Data.Array.GetLit",
             "preresolved": [],
             "info":
             {"original":
              {"trailing": "\n", "pos": 530, "leading": "", "endPos": 552}}}},
           {"node": {"kind": "null", "info": "none", "args": []}}]}},
        {"node":
         {"kind": "Lean.Parser.Module.import",
          "info": "none",
          "args":
          [{"node": {"kind": "null", "info": "none", "args": []}},
           {"atom":
            {"val": "import",
             "info":
             {"original":
              {"trailing": " ", "pos": 553, "leading": "", "endPos": 559}}}},
           {"node": {"kind": "null", "info": "none", "args": []}},
           {"ident":
            {"val": "Init.Data.Array.MapIdx",
             "rawVal": "Init.Data.Array.MapIdx",
             "preresolved": [],
             "info":
             {"original":
              {"trailing": "\n", "pos": 560, "leading": "", "endPos": 582}}}},
           {"node": {"kind": "null", "info": "none", "args": []}}]}},
        {"node":
         {"kind": "Lean.Parser.Module.import",
          "info": "none",
          "args":
          [{"node": {"kind": "null", "info": "none", "args": []}},
           {"atom":
            {"val": "import",
             "info":
             {"original":
              {"trailing": " ", "pos": 583, "leading": "", "endPos": 589}}}},
           {"node": {"kind": "null", "info": "none", "args": []}},
           {"ident":
            {"val": "Init.Data.Array.Set",
             "rawVal": "Init.Data.Array.Set",
             "preresolved": [],
             "info":
             {"original":
              {"trailing": "\n", "pos": 590, "leading": "", "endPos": 609}}}},
           {"node": {"kind": "null", "info": "none", "args": []}}]}},
        {"node":
         {"kind": "Lean.Parser.Module.import",
          "info": "none",
          "args":
          [{"node": {"kind": "null", "info": "none", "args": []}},
           {"atom":
            {"val": "import",
             "info":
             {"original":
              {"trailing": " ", "pos": 610, "leading": "", "endPos": 616}}}},
           {"node": {"kind": "null", "info": "none", "args": []}},
           {"ident":
            {"val": "Init.Data.Array.Monadic",
             "rawVal": "Init.Data.Array.Monadic",
             "preresolved": [],
             "info":
             {"original":
              {"trailing": "\n", "pos": 617, "leading": "", "endPos": 640}}}},
           {"node": {"kind": "null", "info": "none", "args": []}}]}},
        {"node":
         {"kind": "Lean.Parser.Module.import",
          "info": "none",
          "args":
          [{"node": {"kind": "null", "info": "none", "args": []}},
           {"atom":
            {"val": "import",
             "info":
             {"original":
              {"trailing": " ", "pos": 641, "leading": "", "endPos": 647}}}},
           {"node": {"kind": "null", "info": "none", "args": []}},
           {"ident":
            {"val": "Init.Data.Array.FinRange",
             "rawVal": "Init.Data.Array.FinRange",
             "preresolved": [],
             "info":
             {"original":
              {"trailing": "\n", "pos": 648, "leading": "", "endPos": 672}}}},
           {"node": {"kind": "null", "info": "none", "args": []}}]}},
        {"node":
         {"kind": "Lean.Parser.Module.import",
          "info": "none",
          "args":
          [{"node": {"kind": "null", "info": "none", "args": []}},
           {"atom":
            {"val": "import",
             "info":
             {"original":
              {"trailing": " ", "pos": 673, "leading": "", "endPos": 679}}}},
           {"node": {"kind": "null", "info": "none", "args": []}},
           {"ident":
            {"val": "Init.Data.Array.Perm",
             "rawVal": "Init.Data.Array.Perm",
             "preresolved": [],
             "info":
             {"original":
              {"trailing": "\n", "pos": 680, "leading": "", "endPos": 700}}}},
           {"node": {"kind": "null", "info": "none", "args": []}}]}},
        {"node":
         {"kind": "Lean.Parser.Module.import",
          "info": "none",
          "args":
          [{"node": {"kind": "null", "info": "none", "args": []}},
           {"atom":
            {"val": "import",
             "info":
             {"original":
              {"trailing": " ", "pos": 701, "leading": "", "endPos": 707}}}},
           {"node": {"kind": "null", "info": "none", "args": []}},
           {"ident":
            {"val": "Init.Data.Array.Find",
             "rawVal": "Init.Data.Array.Find",
             "preresolved": [],
             "info":
             {"original":
              {"trailing": "\n", "pos": 708, "leading": "", "endPos": 728}}}},
           {"node": {"kind": "null", "info": "none", "args": []}}]}},
        {"node":
         {"kind": "Lean.Parser.Module.import",
          "info": "none",
          "args":
          [{"node": {"kind": "null", "info": "none", "args": []}},
           {"atom":
            {"val": "import",
             "info":
             {"original":
              {"trailing": " ", "pos": 729, "leading": "", "endPos": 735}}}},
           {"node": {"kind": "null", "info": "none", "args": []}},
           {"ident":
            {"val": "Init.Data.Array.Lex",
             "rawVal": "Init.Data.Array.Lex",
             "preresolved": [],
             "info":
             {"original":
              {"trailing": "\n", "pos": 736, "leading": "", "endPos": 755}}}},
           {"node": {"kind": "null", "info": "none", "args": []}}]}},
        {"node":
         {"kind": "Lean.Parser.Module.import",
          "info": "none",
          "args":
          [{"node": {"kind": "null", "info": "none", "args": []}},
           {"atom":
            {"val": "import",
             "info":
             {"original":
              {"trailing": " ", "pos": 756, "leading": "", "endPos": 762}}}},
           {"node": {"kind": "null", "info": "none", "args": []}},
           {"ident":
            {"val": "Init.Data.Array.Range",
             "rawVal": "Init.Data.Array.Range",
             "preresolved": [],
             "info":
             {"original":
              {"trailing": "\n", "pos": 763, "leading": "", "endPos": 784}}}},
           {"node": {"kind": "null", "info": "none", "args": []}}]}},
        {"node":
         {"kind": "Lean.Parser.Module.import",
          "info": "none",
          "args":
          [{"node": {"kind": "null", "info": "none", "args": []}},
           {"atom":
            {"val": "import",
             "info":
             {"original":
              {"trailing": " ", "pos": 785, "leading": "", "endPos": 791}}}},
           {"node": {"kind": "null", "info": "none", "args": []}},
           {"ident":
            {"val": "Init.Data.Array.Erase",
             "rawVal": "Init.Data.Array.Erase",
             "preresolved": [],
             "info":
             {"original":
              {"trailing": "\n", "pos": 792, "leading": "", "endPos": 813}}}},
           {"node": {"kind": "null", "info": "none", "args": []}}]}},
        {"node":
         {"kind": "Lean.Parser.Module.import",
          "info": "none",
          "args":
          [{"node": {"kind": "null", "info": "none", "args": []}},
           {"atom":
            {"val": "import",
             "info":
             {"original":
              {"trailing": " ", "pos": 814, "leading": "", "endPos": 820}}}},
           {"node": {"kind": "null", "info": "none", "args": []}},
           {"ident":
            {"val": "Init.Data.Array.Zip",
             "rawVal": "Init.Data.Array.Zip",
             "preresolved": [],
             "info":
             {"original":
              {"trailing": "\n", "pos": 821, "leading": "", "endPos": 840}}}},
           {"node": {"kind": "null", "info": "none", "args": []}}]}},
        {"node":
         {"kind": "Lean.Parser.Module.import",
          "info": "none",
          "args":
          [{"node": {"kind": "null", "info": "none", "args": []}},
           {"atom":
            {"val": "import",
             "info":
             {"original":
              {"trailing": " ", "pos": 841, "leading": "", "endPos": 847}}}},
           {"node": {"kind": "null", "info": "none", "args": []}},
           {"ident":
            {"val": "Init.Data.Array.InsertIdx",
             "rawVal": "Init.Data.Array.InsertIdx",
             "preresolved": [],
             "info":
             {"original":
              {"trailing": "\n", "pos": 848, "leading": "", "endPos": 873}}}},
           {"node": {"kind": "null", "info": "none", "args": []}}]}},
        {"node":
         {"kind": "Lean.Parser.Module.import",
          "info": "none",
          "args":
          [{"node": {"kind": "null", "info": "none", "args": []}},
           {"atom":
            {"val": "import",
             "info":
             {"original":
              {"trailing": " ", "pos": 874, "leading": "", "endPos": 880}}}},
           {"node": {"kind": "null", "info": "none", "args": []}},
           {"ident":
            {"val": "Init.Data.Array.Extract",
             "rawVal": "Init.Data.Array.Extract",
             "preresolved": [],
             "info":
             {"original":
              {"trailing": "\n", "pos": 881, "leading": "", "endPos": 904}}}},
           {"node": {"kind": "null", "info": "none", "args": []}}]}}]}}]}}]}