{"tactics": [],
 "premises": [],
 "commandASTs":
 [{"node":
   {"kind": "Lean.Parser.Module.header",
    "info": "none",
    "args":
    [{"node":
      {"kind": "null",
       "info": "none",
       "args":
       [{"node":
         {"kind": "Lean.Parser.Module.moduleTk",
          "info": "none",
          "args":
          [{"atom":
            {"val": "module",
             "info":
             {"original":
              {"trailing": "\n\n",
               "pos": 151,
               "leading": "",
               "endPos": 157}}}}]}}]}},
     {"node":
      {"kind": "null",
       "info": "none",
       "args":
       [{"node":
         {"kind": "Lean.Parser.Module.prelude",
          "info": "none",
          "args":
          [{"atom":
            {"val": "prelude",
             "info":
             {"original":
              {"trailing": "\n",
               "pos": 159,
               "leading": "",
               "endPos": 166}}}}]}}]}},
     {"node":
      {"kind": "null",
       "info": "none",
       "args":
       [{"node":
         {"kind": "Lean.Parser.Module.import",
          "info": "none",
          "args":
          [{"node": {"kind": "null", "info": "none", "args": []}},
           {"atom":
            {"val": "import",
             "info":
             {"original":
              {"trailing": " ", "pos": 167, "leading": "", "endPos": 173}}}},
           {"node": {"kind": "null", "info": "none", "args": []}},
           {"ident":
            {"val": "Init.Data.BitVec.Basic",
             "rawVal": "Init.Data.BitVec.Basic",
             "preresolved": [],
             "info":
             {"original":
              {"trailing": "\n", "pos": 174, "leading": "", "endPos": 196}}}},
           {"node": {"kind": "null", "info": "none", "args": []}}]}},
        {"node":
         {"kind": "Lean.Parser.Module.import",
          "info": "none",
          "args":
          [{"node": {"kind": "null", "info": "none", "args": []}},
           {"atom":
            {"val": "import",
             "info":
             {"original":
              {"trailing": " ", "pos": 197, "leading": "", "endPos": 203}}}},
           {"node": {"kind": "null", "info": "none", "args": []}},
           {"ident":
            {"val": "Init.Data.BitVec.Bitblast",
             "rawVal": "Init.Data.BitVec.Bitblast",
             "preresolved": [],
             "info":
             {"original":
              {"trailing": "\n", "pos": 204, "leading": "", "endPos": 229}}}},
           {"node": {"kind": "null", "info": "none", "args": []}}]}},
        {"node":
         {"kind": "Lean.Parser.Module.import",
          "info": "none",
          "args":
          [{"node": {"kind": "null", "info": "none", "args": []}},
           {"atom":
            {"val": "import",
             "info":
             {"original":
              {"trailing": " ", "pos": 230, "leading": "", "endPos": 236}}}},
           {"node": {"kind": "null", "info": "none", "args": []}},
           {"ident":
            {"val": "Init.Data.BitVec.Folds",
             "rawVal": "Init.Data.BitVec.Folds",
             "preresolved": [],
             "info":
             {"original":
              {"trailing": "\n", "pos": 237, "leading": "", "endPos": 259}}}},
           {"node": {"kind": "null", "info": "none", "args": []}}]}},
        {"node":
         {"kind": "Lean.Parser.Module.import",
          "info": "none",
          "args":
          [{"node": {"kind": "null", "info": "none", "args": []}},
           {"atom":
            {"val": "import",
             "info":
             {"original":
              {"trailing": " ", "pos": 260, "leading": "", "endPos": 266}}}},
           {"node": {"kind": "null", "info": "none", "args": []}},
           {"ident":
            {"val": "Init.Data.BitVec.Lemmas",
             "rawVal": "Init.Data.BitVec.Lemmas",
             "preresolved": [],
             "info":
             {"original":
              {"trailing": "\n", "pos": 267, "leading": "", "endPos": 290}}}},
           {"node": {"kind": "null", "info": "none", "args": []}}]}}]}}]}}]}